{"stats":{"minecraft:crafted":{"minecraft:oak_planks":4,"minecraft:cobblestone_slab":6,"minecraft:torch":20,"minecraft:crafting_table":1,"minecraft:stick":12,"minecraft:wooden_pickaxe":1,"minecraft:stone_pickaxe":2},"minecraft:broken":{"minecraft:wooden_pickaxe":1},"minecraft:picked_up":{"minecraft:gravel":2,"minecraft:oak_log":17,"minecraft:oak_sapling":2,"minecraft:coal":23,"minecraft:oak_planks":12,"minecraft:cobblestone":158},"minecraft:used":{"minecraft:torch":7,"minecraft:crafting_table":1,"minecraft:stone_pickaxe":130,"minecraft:wooden_pickaxe":59},"minecraft:mined":{"minecraft:grass":1,"minecraft:oak_log":17,"minecraft:coal_ore":23,"minecraft:stone":166,"minecraft:oak_leaves":3},"minecraft:custom":{"minecraft:time_since_rest":11445,"minecraft:play_time":11445,"minecraft:sprint_one_cm":9082,"minecraft:damage_taken":30,"minecraft:walk_one_cm":10049,"minecraft:jump":52,"minecraft:damage_dealt":10,"minecraft:leave_game":2,"minecraft:time_since_death":11445,"minecraft:total_world_time":11445,"minecraft:interact_with_crafting_table":3,"minecraft:fall_one_cm":1035,"minecraft:fly_one_cm":5385}},"DataVersion":2730}